{
  "entrypoints": {
    "app": {
      "js": [
        "/build/runtime.c2b5f79a.js",
        "/build/23.ffdaa620.js",
        "/build/363.5ca46b49.js",
        "/build/app.825d16f2.js"
      ],
      "css": [
        "/build/app.b75294ae.css"
      ]
    },
    "index": {
      "js": [
        "/build/runtime.c2b5f79a.js",
        "/build/660.e516ad98.js",
        "/build/23.ffdaa620.js",
        "/build/622.f592eb5d.js",
        "/build/index.d29cedf5.js"
      ]
    },
    "home": {
      "js": [
        "/build/runtime.c2b5f79a.js",
        "/build/660.e516ad98.js",
        "/build/home.69cee111.js"
      ]
    }
  }
}